README.md
cubedol3.py
setup.py
cubedol3.egg-info/PKG-INFO
cubedol3.egg-info/SOURCES.txt
cubedol3.egg-info/dependency_links.txt
cubedol3.egg-info/top_level.txt